cdk_noob/__init__.py
cdk_noob/py.typed
cdk_noob/_jsii/__init__.py
cdk_noob/_jsii/cdk-noob@0.1.3.jsii.tgz
cdk_noob-0.1.3.dist-info/METADATA
cdk_noob-0.1.3.dist-info/WHEEL
cdk_noob-0.1.3.dist-info/top_level.txt
cdk_noob-0.1.3.dist-info/RECORD
