Metadata-Version: 2.1
Name: cdk-noob
Version: 0.1.3
Summary: cdk-noob
Home-page: https://github.com/bgreengo/cdk-noob
Author: Blake Green<blakegreen@msn.com>
License: Apache-2.0
Project-URL: Source, https://github.com/bgreengo/cdk-noob
Platform: UNKNOWN
Classifier: Intended Audience :: Developers
Classifier: Operating System :: OS Independent
Classifier: Programming Language :: JavaScript
Classifier: Programming Language :: Python :: 3 :: Only
Classifier: Programming Language :: Python :: 3.6
Classifier: Programming Language :: Python :: 3.7
Classifier: Programming Language :: Python :: 3.8
Classifier: Typing :: Typed
Classifier: Development Status :: 5 - Production/Stable
Classifier: License :: OSI Approved
Requires-Python: >=3.6
Requires-Dist: aws-cdk.aws-ec2 (<2.0.0,>=1.73.0)
Requires-Dist: aws-cdk.aws-ecs-patterns (<2.0.0,>=1.73.0)
Requires-Dist: aws-cdk.aws-ecs (<2.0.0,>=1.73.0)
Requires-Dist: aws-cdk.core (<2.0.0,>=1.73.0)
Requires-Dist: constructs (<4.0.0,>=3.2.27)
Requires-Dist: jsii (<2.0.0,>=1.14.1)
Requires-Dist: publication (>=0.0.3)
